{
  "Invoice_Header_Fields": {
    "FileName": "KF DC EDISON (Y-340)",
    "SourceOrderID": null,
    "PONumber": "300571152",
    "RDD": "2025/05/07",
    "ShippingAddress": "KF DC EDISON (Y-340)\n31 MILL ROAD\nEDISON, NJ 08837",
    "BillingAddress": "FRITO LAY INC\n10880 LIN PAGE PLACE\nSAINT LOUIS, MO 63132"
  },
  "Line_Item_Fields": {
    "MaterialIDList": [
      "80005365",
      "80008042",
      "10354",
      "10446",
      "10513",
      "10514",
      "10525",
      "7689"
    ],
    "MaterialIDCount": 8,
    "LineItemCount": 8
  },
  "Validation_and_Quality_Checks": {
    "Count>0": true,
    "LineItem=IDs": true,
    "Length>5": true,
    "OnlyNumeric": true,
    "All Mandatory Fields extracted": true
  },
  "Confidence_and_Validation": {
    "overall_confidence": 0.8125,
    "needs_human_review": true,
    "validation_errors": [
      "SourceOrderID: Missing/null",
      "ShippingAddress: Not found in OCR (possible hallucination)",
      "BillingAddress: Not found in OCR (possible hallucination)"
    ]
  }
}